expression/src/__init__.py
expression/src/condition.py
expression/src/enclosure.py
expression/src/evaluate.py
expression/src/expression.py
expression/src/handler.py
python_expression-0.1.dist-info/METADATA
python_expression-0.1.dist-info/WHEEL
python_expression-0.1.dist-info/top_level.txt
python_expression-0.1.dist-info/RECORD
