Metadata-Version: 2.1
Name: python-expression
Version: 0.1
Summary: 
Home-page: https://github.com/mwayi/python-expression
Author: Mwayi Dzanjalimodzi
Author-email: mr.mwayi@gmail.com
License: MIT
Platform: UNKNOWN
